dad_tool/__init__.py
dad_tool/_version.py
dad_tool/data_router.py
dad_tool/py.typed
dad_tool/dad/src/addresses/australia/vt-addresses.json
dad_tool/dad/src/addresses/australia/vt-addresses.min.json
dad_tool/dad/src/addresses/canada/bc-addresses.json
dad_tool/dad/src/addresses/canada/bc-addresses.min.json
dad_tool/dad/src/addresses/china/bj-addresses.json
dad_tool/dad/src/addresses/china/bj-addresses.min.json
dad_tool/dad/src/addresses/china/hk-addresses.json
dad_tool/dad/src/addresses/china/hk-addresses.min.json
dad_tool/dad/src/addresses/europe/de-addresses.json
dad_tool/dad/src/addresses/europe/de-addresses.min.json
dad_tool/dad/src/addresses/europe/es-addresses.json
dad_tool/dad/src/addresses/europe/es-addresses.min.json
dad_tool/dad/src/addresses/europe/fr-addresses.json
dad_tool/dad/src/addresses/europe/fr-addresses.min.json
dad_tool/dad/src/addresses/europe/uk-addresses.json
dad_tool/dad/src/addresses/europe/uk-addresses.min.json
dad_tool/dad/src/addresses/mexico/mx-addresses.json
dad_tool/dad/src/addresses/mexico/mx-addresses.min.json
dad_tool/dad/src/addresses/united-states/az-addresses.json
dad_tool/dad/src/addresses/united-states/az-addresses.min.json
dad_tool/dad/src/addresses/united-states/ca-addresses.json
dad_tool/dad/src/addresses/united-states/ca-addresses.min.json
dad_tool/dad/src/addresses/united-states/id-addresses.json
dad_tool/dad/src/addresses/united-states/id-addresses.min.json
dad_tool/dad/src/addresses/united-states/ks-addresses.json
dad_tool/dad/src/addresses/united-states/ks-addresses.min.json
dad_tool/dad/src/addresses/united-states/nv-addresses.json
dad_tool/dad/src/addresses/united-states/nv-addresses.min.json
dad_tool/dad/src/addresses/united-states/ny-addresses.json
dad_tool/dad/src/addresses/united-states/ny-addresses.min.json
dad_tool/dad/src/addresses/united-states/or-addresses.json
dad_tool/dad/src/addresses/united-states/or-addresses.min.json
dad_tool/dad/src/addresses/united-states/tx-addresses.json
dad_tool-3.0.0.dist-info/licenses/LICENSE
dad_tool-3.0.0.dist-info/METADATA
dad_tool-3.0.0.dist-info/WHEEL
dad_tool-3.0.0.dist-info/top_level.txt
dad_tool-3.0.0.dist-info/RECORD
